{
  "schemaVersion": 1,
  "workflow_file": "docs/ai/specs/.process/TACD-001-workflow.md",
  "workflow_files": [
    "docs/ai/specs/.process/TACD-001-workflow.md"
  ],
  "feature_dir": "specs/tacd-001-platform-mechanics-spike",
  "feature_dirs": [
    "specs/tacd-001-platform-mechanics-spike"
  ],
  "feature_branch": "codex/tacd-001-post-merge-hygiene",
  "updated_at": "2026-06-18T01:37:02Z",
  "active_step": "Archived",
  "status": "completed",
  "archive_sweep": {
    "status": "completed",
    "archive_extension_installed": true,
    "cleanup_mode": "post-merge-hygiene",
    "current_target": null,
    "excluded_current_spec": null,
    "eligible_previous_specs": [
      "specs/tacd-001-platform-mechanics-spike"
    ],
    "safeToApplyCleanup": true,
    "dryRunProvenanceOnly": false,
    "archive_report": ".specify/memory/archive-reports/2026-06-18-tacd-001-post-merge-hygiene.md",
    "cleanup_applied": true
  },
  "implementation": {
    "status": "completed",
    "gate": "G7",
    "gate_status": "passed",
    "completed_specs": [
      {
        "spec_id": "TACD-001",
        "merged_prs": [
          211,
          212,
          213,
          214,
          216
        ],
        "merge_commits": [
          "2104432cb8d92c0088b99f02e0922d5ebf433a98",
          "e9d3c08af55658b97452c86c294bae0b340a3bc4",
          "dfa18a20691b86724cc05008c2b3fae93a0d9127",
          "46d01dcf081a8c416c692db497daea5cae11a801",
          "62dc58a46419ed09c1aa506974ef8c7fbab998ee"
        ],
        "canonical_report": "docs/ai/research/tool-agnostic-capability-discovery-spike.md",
        "canonical_prd": "docs/prd-tool-agnostic-capability-discovery.md",
        "canonical_roadmap": "docs/ai/specs/tool-agnostic-capability-discovery-technical-roadmap.md",
        "canonical_moc": "docs/ai/specs/tool-agnostic-capability-discovery-roadmap-MOC.md",
        "verification": {
          "default_suite": "passed before PR merge",
          "github_checks": "passed on PRs #214 and #216",
          "archive_cleanup": "passed in codex/tacd-001-post-merge-hygiene"
        }
      }
    ]
  },
  "next_specs": [
    "TACD-002",
    "TACD-003",
    "TACD-004"
  ],
  "project_commands": {
    "BUILD": "N/A",
    "TYPECHECK": "N/A",
    "LINT": "N/A",
    "LINT_FIX": "N/A",
    "UNIT_TEST": "N/A",
    "INTEGRATION_TEST": "N/A",
    "SINGLE_FILE_TEST": "N/A",
    "SINGLE_FILE_INTEGRATION": "N/A",
    "FULL_VERIFY": "bash tests/speckit-pro/run-all.sh"
  }
}
